<annotation>
	<folder>transfer learning</folder>
	<filename>37.jpg</filename>
	<path>E:\CodeExercise\tf\traffic signs\transfer learning\37.jpg</path>
	<source>
		<database>Unknown</database>
	</source>
	<size>
		<width>4080</width>
		<height>3060</height>
		<depth>3</depth>
	</size>
	<segmented>0</segmented>
	<object>
		<name>thirty</name>
		<pose>Unspecified</pose>
		<truncated>0</truncated>
		<difficult>0</difficult>
		<bndbox>
			<xmin>48</xmin>
			<ymin>913</ymin>
			<xmax>525</xmax>
			<ymax>1327</ymax>
		</bndbox>
	</object>
	<object>
		<name>cycle</name>
		<pose>Unspecified</pose>
		<truncated>0</truncated>
		<difficult>0</difficult>
		<bndbox>
			<xmin>895</xmin>
			<ymin>933</ymin>
			<xmax>1402</xmax>
			<ymax>1397</ymax>
		</bndbox>
	</object>
	<object>
		<name>ban</name>
		<pose>Unspecified</pose>
		<truncated>0</truncated>
		<difficult>0</difficult>
		<bndbox>
			<xmin>1552</xmin>
			<ymin>857</ymin>
			<xmax>1885</xmax>
			<ymax>1177</ymax>
		</bndbox>
	</object>
	<object>
		<name>P</name>
		<pose>Unspecified</pose>
		<truncated>0</truncated>
		<difficult>0</difficult>
		<bndbox>
			<xmin>2128</xmin>
			<ymin>1133</ymin>
			<xmax>2555</xmax>
			<ymax>1587</ymax>
		</bndbox>
	</object>
	<object>
		<name>train</name>
		<pose>Unspecified</pose>
		<truncated>0</truncated>
		<difficult>0</difficult>
		<bndbox>
			<xmin>2555</xmin>
			<ymin>893</ymin>
			<xmax>2945</xmax>
			<ymax>1270</ymax>
		</bndbox>
	</object>
	<object>
		<name>first</name>
		<pose>Unspecified</pose>
		<truncated>0</truncated>
		<difficult>0</difficult>
		<bndbox>
			<xmin>3232</xmin>
			<ymin>1150</ymin>
			<xmax>3745</xmax>
			<ymax>1633</ymax>
		</bndbox>
	</object>
</annotation>
